[
    {
        "nie": "0182022025",
        "nombres": "Edward Edenilson",
        "apellidos": "Martinez"
    },
    {
        "nie": "0232022025",
        "nombres": "Daniel ALexander",
        "apellidos": "Alas Sanchez"
    },
    {
        "nie": "48397223",
        "nombres": "Josue Enrique",
        "apellidos": "Guzman Bonilla"
    },
    {
        "nie": "3670126",
        "nombres": "Daniel",
        "apellidos": "Alas"
    },
    {
        "nie": "3670136",
        "nombres": "Iverson",
        "apellidos": "Zepeda"
    }
]